spaceman/__init__.py
spaceman/main.py
spaceman/meta.py
spaceman/serializer.py
spaceman/store.py
spaceman-0.2.3.dist-info/DESCRIPTION.rst
spaceman-0.2.3.dist-info/METADATA
spaceman-0.2.3.dist-info/RECORD
spaceman-0.2.3.dist-info/WHEEL
spaceman-0.2.3.dist-info/metadata.json
spaceman-0.2.3.dist-info/top_level.txt
